Metadata-Version: 2.1
Name: synthmap
Version: 0.2.220620
Summary: A toolkit to recover geodata from collections of images
Home-page: https://theaom.ai
Author: Benoît Drumain
Author-email: ben@theaom.ai
Project-URL: Bug Tracker, https://github.com/theaomben/synthmap/issues
Classifier: Programming Language :: Python :: 3
Classifier: License :: Freely Distributable
Classifier: Operating System :: OS Independent
Classifier: Development Status :: 2 - Pre-Alpha
Classifier: Environment :: Console
Classifier: Environment :: Web Environment
Classifier: Intended Audience :: Developers
Classifier: Intended Audience :: Science/Research
Classifier: Topic :: Multimedia :: Graphics :: 3D Modeling
Classifier: Topic :: Scientific/Engineering :: GIS
Requires-Python: >=3.10
License-File: LICENSE
Requires-Dist: anyio
Requires-Dist: argon2-cffi
Requires-Dist: argon2-cffi-bindings
Requires-Dist: asgiref
Requires-Dist: astroid
Requires-Dist: atomicwrites
Requires-Dist: attrs
Requires-Dist: beautifulsoup4
Requires-Dist: black
Requires-Dist: certifi
Requires-Dist: cffi
Requires-Dist: charset-normalizer
Requires-Dist: click
Requires-Dist: colorama
Requires-Dist: commonmark
Requires-Dist: dill
Requires-Dist: fastapi
Requires-Dist: h11
Requires-Dist: idna
Requires-Dist: iniconfig
Requires-Dist: isort
Requires-Dist: Jinja2
Requires-Dist: lazy-object-proxy
Requires-Dist: MarkupSafe
Requires-Dist: mccabe
Requires-Dist: mypy-extensions
Requires-Dist: numpy
Requires-Dist: opencv-python
Requires-Dist: packaging
Requires-Dist: pathspec
Requires-Dist: platformdirs
Requires-Dist: pluggy
Requires-Dist: py
Requires-Dist: pycparser
Requires-Dist: pydantic
Requires-Dist: Pygments
Requires-Dist: pylint
Requires-Dist: PyNaCl
Requires-Dist: pyparsing
Requires-Dist: pytest
Requires-Dist: python-multipart
Requires-Dist: python-dotenv
Requires-Dist: requests
Requires-Dist: rich
Requires-Dist: rich-click
Requires-Dist: sniffio
Requires-Dist: starlette
Requires-Dist: tomli
Requires-Dist: typing-extensions
Requires-Dist: urllib3
Requires-Dist: uvicorn
Requires-Dist: wrapt
